cube/__init__.py
cube/api.py
cube/story.py
cube/io_utils/__init__.py
cube/io_utils/audio.py
cube/io_utils/dataset.py
cube/io_utils/encodings.py
cube/io_utils/io_cubegan.py
cube/io_utils/io_phonemizer.py
cube/io_utils/io_text.py
cube/io_utils/io_textcoder.py
cube/io_utils/io_vocoder.py
cube/io_utils/repository.py
cube/io_utils/runtime.py
cube/io_utils/vocoder.py
cube/networks/__init__.py
cube/networks/cubegan.py
cube/networks/g2p.py
cube/networks/loss.py
cube/networks/modules.py
cube/networks/phonemizer.py
cube/networks/textcoder.py
cube/networks/vocoder.py
cube/utils/__init__.py
cube/utils/hf.py
hifigan/__init__.py
hifigan/env.py
hifigan/inference.py
hifigan/inference_e2e.py
hifigan/meldataset.py
hifigan/models.py
hifigan/train.py
hifigan/utils.py
ttscube-0.1.0.0.dist-info/LICENSE
ttscube-0.1.0.0.dist-info/METADATA
ttscube-0.1.0.0.dist-info/WHEEL
ttscube-0.1.0.0.dist-info/top_level.txt
ttscube-0.1.0.0.dist-info/RECORD
