Metadata-Version: 2.1
Name: ttscube
Version: 0.1.0.0
Summary: Text-to-speech synthesis engine, based on end-to-end GAN training. Features: multilanguage, multispeaker, realtime CPU synthesis
Home-page: https://github.com/tiberiu44/TTS-Cube
Author: Multiple authors
Author-email: tiberiu44@gmail.com
Classifier: Programming Language :: Python :: 3.0
Classifier: License :: OSI Approved :: Apache Software License
Classifier: Operating System :: OS Independent
License-File: LICENSE
Requires-Dist: fasttext ==0.9.2
Requires-Dist: ipdb ==0.13.13
Requires-Dist: librosa ==0.10.1
Requires-Dist: matplotlib ==3.8.4
Requires-Dist: numpy ==1.26.4
Requires-Dist: Pillow ==10.3.0
Requires-Dist: pysndfx ==0.3.6
Requires-Dist: pysptk ==0.2.2
Requires-Dist: pytorch-lightning ==2.2.1
Requires-Dist: PyYAML ==6.0.1
Requires-Dist: Requests ==2.31.0
Requires-Dist: scipy ==1.13.0
Requires-Dist: setuptools ==69.2.0
Requires-Dist: soundfile ==0.12.1
Requires-Dist: TextGrid ==1.6.1
Requires-Dist: torch ==2.2.2
Requires-Dist: tqdm ==4.66.2
Requires-Dist: transformers ==4.39.3
